[
  {
    "place_id": "ChIJ0yZ68jwFl0cRj2zUWQTL0YQ",
    "name": "DEXA Knochendichtemessung Karlsruhe – Radiologie Ettlingen",
    "formattedAddress": "Wilhelmstraße 1, 76275 Ettlingen, Germany",
    "location": {
      "lat": 48.93900860000001,
      "lng": 8.4107865
    },
    "website": "https://praxis-auskunft.de/dexa-knochendichtemessung-karlsruhe/",
    "phone": "+49 7243 14240",
    "rating": 5,
    "types": [
      "medical_clinic",
      "doctor",
      "health",
      "point_of_interest",
      "establishment"
    ],
    "status": "OPERATIONAL",
    "sources": ["grid:dexa"],
    "source": "google_places",
    "confidenceScore": 8430,
    "fetchedAt": "2026-02-24T13:10:10.171Z",
    "searchContext": {
      "pipeline": "dexa",
      "tileId": "base_0",
      "keyword": "DEXA",
      "depth": 0,
      "coordinates": "47.35,6.05"
    },
    "category": "dexa_candidate",
    "classifiedAt": "2026-02-24T13:50:15.995Z",
    "verification": {
      "verified": true,
      "matchedKeywords": ["dexa"],
      "confidenceScore": 0.4,
      "pagesScanned": 2
    },
    "selfPay": false,
    "categoryLabel": "DEXA"
  },
  {
    "place_id": "ChIJV7Ws8GKZwEcR-xMcNbDxx-Q",
    "name": "Knochendichtemessung (DXA) Aachen | Radiologie Heinrichsallee",
    "formattedAddress": "Heinrichsallee 50, 52062 Aachen, Germany",
    "location": {
      "lat": 50.776944,
      "lng": 6.095230099999999
    },
    "website": "https://www.radiologie-ac.de/leistungen/knochendichtemessung-dxa-aachen/",
    "phone": "+49 241 946950",
    "rating": null,
    "types": ["doctor", "health", "point_of_interest", "establishment"],
    "status": "OPERATIONAL",
    "sources": ["grid:dexa"],
    "source": "google_places",
    "confidenceScore": 0,
    "fetchedAt": "2026-02-24T13:10:22.480Z",
    "searchContext": {
      "pipeline": "dexa",
      "tileId": "base_4",
      "keyword": "DXA",
      "depth": 0,
      "coordinates": "47.35,7.25"
    },
    "category": "dexa_candidate",
    "classifiedAt": "2026-02-24T13:50:16.009Z",
    "verification": {
      "verified": true,
      "matchedKeywords": ["dexa"],
      "confidenceScore": 0.5,
      "pagesScanned": 9
    },
    "selfPay": false,
    "categoryLabel": "DEXA"
  },
  {
    "place_id": "ChIJH1t0owR1nkcRDtnjWYuyGXA",
    "name": "Osteoporosezentrum München",
    "formattedAddress": "Pienzenauerstraße 14, 81679 München, Germany",
    "location": {
      "lat": 48.151697299999995,
      "lng": 11.603262899999999
    },
    "website": "https://www.osteoporosezentrum.de/",
    "phone": "+49 89 592524",
    "rating": 4.9,
    "types": ["health", "point_of_interest", "establishment"],
    "status": "OPERATIONAL",
    "sources": ["grid:dexa"],
    "source": "google_places",
    "confidenceScore": 0,
    "fetchedAt": "2026-02-24T13:11:55.300Z",
    "searchContext": {
      "pipeline": "dexa",
      "tileId": "base_79",
      "keyword": "DXA",
      "depth": 0,
      "coordinates": "47.95,11.15"
    },
    "category": "dexa_candidate",
    "classifiedAt": "2026-02-24T13:50:16.012Z",
    "verification": {
      "verified": true,
      "matchedKeywords": ["muskelmasse"],
      "confidenceScore": 0.25,
      "pagesScanned": 9
    },
    "selfPay": false,
    "categoryLabel": "DEXA"
  },
  {
    "place_id": "ChIJ7TIJdWftmUcRvbWTEuc1pw4",
    "name": "Praxis für Körperanalysen - Darmkur - Ernährung - Entgiftung",
    "formattedAddress": "Pfleghofstraße 43, 72555 Metzingen, Germany",
    "location": {
      "lat": 48.537423999999994,
      "lng": 9.285423999999999
    },
    "website": "https://www.balance-oase.com/",
    "phone": "+49 7123 9634300",
    "rating": 5,
    "types": ["doctor", "health", "point_of_interest", "establishment"],
    "status": "OPERATIONAL",
    "sources": ["grid:dexa"],
    "source": "google_places",
    "confidenceScore": 0,
    "fetchedAt": "2026-02-24T13:13:24.007Z",
    "searchContext": {
      "pipeline": "dexa",
      "tileId": "base_166",
      "keyword": "Körperanalyse",
      "depth": 0,
      "coordinates": "48.85,9.35"
    },
    "category": "blood_candidate",
    "classifiedAt": "2026-02-24T13:50:16.015Z",
    "verification": {
      "verified": true,
      "matchedKeywords": ["blutabnahme"],
      "confidenceScore": 0.25,
      "pagesScanned": 1
    },
    "selfPay": false,
    "categoryLabel": "Blutlabor"
  },
  {
    "place_id": "ChIJSwnlA-60CUcRQa1nVLxZTls",
    "name": "Knochendichtemessung Praxiszentrum Rödertal",
    "formattedAddress": "Großmannstraße 5, 01900 Großröhrsdorf, Germany",
    "location": {
      "lat": 51.146459899999996,
      "lng": 14.0196387
    },
    "website": "https://www.boden-praxis.de/sportorthopaedie-knochendichtemessung/",
    "phone": "+49 35952 44796",
    "rating": 1,
    "types": ["health", "point_of_interest", "establishment"],
    "status": "OPERATIONAL",
    "sources": ["grid:dexa"],
    "source": "google_places",
    "confidenceScore": 0,
    "fetchedAt": "2026-02-24T13:17:43.213Z",
    "searchContext": {
      "pipeline": "dexa",
      "tileId": "base_397",
      "keyword": "Ganzkörper DEXA",
      "depth": 0,
      "coordinates": "50.95,13.55"
    },
    "category": "dexa_candidate",
    "classifiedAt": "2026-02-24T13:50:16.052Z",
    "verification": {
      "verified": true,
      "matchedKeywords": ["muskelmasse"],
      "confidenceScore": 0.25,
      "pagesScanned": 2
    },
    "selfPay": false,
    "categoryLabel": "DEXA"
  },
  {
    "place_id": "ChIJF4Ig2Z7hvkcR7mMDLE0Bqm0",
    "name": "SYNLAB MVZ Bonn",
    "formattedAddress": "Dechenstraße 1, 53115 Bonn, Germany",
    "location": {
      "lat": 50.731316199999995,
      "lng": 7.096895399999999
    },
    "website": "https://www.synlab.de/lab/bonn",
    "phone": "+49 228 555260",
    "rating": 4.4,
    "types": ["medical_lab", "health", "point_of_interest", "establishment"],
    "status": "OPERATIONAL",
    "sources": ["grid:blood"],
    "source": "google_places",
    "confidenceScore": 0,
    "fetchedAt": "2026-02-24T13:20:17.509Z",
    "searchContext": {
      "pipeline": "blood",
      "tileId": "base_0",
      "keyword": "Bluttest",
      "depth": 0,
      "coordinates": "47.35,6.05"
    },
    "category": "blood_candidate",
    "classifiedAt": "2026-02-24T13:50:16.053Z",
    "verification": {
      "verified": true,
      "matchedKeywords": ["selbstzahler"],
      "confidenceScore": 0.25,
      "pagesScanned": 9
    },
    "prices": ["rivat bezahlt werden. Der Preis beträgt 169,03 €"],
    "selfPay": true,
    "categoryLabel": "Blutlabor"
  },
  {
    "place_id": "ChIJ4-lanCglv0cRWEuGpk1HY3o",
    "name": "MVZ Labor Dr. Quade & Kollegen GmbH",
    "formattedAddress": "Hugo-Eckener-Straße 45, 50829 Köln, Germany",
    "location": {
      "lat": 50.9770359,
      "lng": 6.8854248
    },
    "website": "https://www.lab-quade.de/",
    "phone": "+49 221 9405640",
    "rating": 3.7,
    "types": ["medical_lab", "health", "point_of_interest", "establishment"],
    "status": "OPERATIONAL",
    "sources": ["grid:blood"],
    "source": "google_places",
    "confidenceScore": 0,
    "fetchedAt": "2026-02-24T13:20:17.509Z",
    "searchContext": {
      "pipeline": "blood",
      "tileId": "base_0",
      "keyword": "Bluttest",
      "depth": 0,
      "coordinates": "47.35,6.05"
    },
    "category": "blood_candidate",
    "classifiedAt": "2026-02-24T13:50:16.053Z",
    "verification": {
      "verified": true,
      "matchedKeywords": ["laboranalyse"],
      "confidenceScore": 0.25,
      "pagesScanned": 4
    },
    "selfPay": false,
    "categoryLabel": "Blutlabor"
  },
  {
    "place_id": "ChIJtY-LAxL-vEcRQIlZQYJXwnU",
    "name": "SYNLAB MVZ Bad Nauheim",
    "formattedAddress": "In d. Hub 5, 61231 Bad Nauheim, Germany",
    "location": {
      "lat": 50.35393680000001,
      "lng": 8.7534092
    },
    "website": "https://www.synlab.de/lab/bad-nauheim",
    "phone": "+49 6032 91120",
    "rating": 4.8,
    "types": ["medical_lab", "health", "point_of_interest", "establishment"],
    "status": "OPERATIONAL",
    "sources": ["grid:blood"],
    "source": "google_places",
    "confidenceScore": 0,
    "fetchedAt": "2026-02-24T13:20:17.509Z",
    "searchContext": {
      "pipeline": "blood",
      "tileId": "base_0",
      "keyword": "Bluttest",
      "depth": 0,
      "coordinates": "47.35,6.05"
    },
    "category": "blood_candidate",
    "classifiedAt": "2026-02-24T13:50:16.053Z",
    "verification": {
      "verified": true,
      "matchedKeywords": ["selbstzahler"],
      "confidenceScore": 0.25,
      "pagesScanned": 9
    },
    "prices": ["rivat bezahlt werden. Der Preis beträgt 169,03 €"],
    "selfPay": true,
    "categoryLabel": "Blutlabor"
  },
  {
    "place_id": "ChIJuSZqb8dRqEcRVge6_dat75g",
    "name": "Mein Labor Berlin",
    "formattedAddress": "Sylter Str. 2, 13353 Berlin, Germany",
    "location": {
      "lat": 52.541562899999995,
      "lng": 13.338062599999999
    },
    "website": "https://mein.laborberlin.com/",
    "phone": "+49 30 405026800",
    "rating": 5,
    "types": ["medical_lab", "health", "point_of_interest", "establishment"],
    "status": "OPERATIONAL",
    "sources": ["grid:blood"],
    "source": "google_places",
    "confidenceScore": 0,
    "fetchedAt": "2026-02-24T13:20:17.509Z",
    "searchContext": {
      "pipeline": "blood",
      "tileId": "base_0",
      "keyword": "Bluttest",
      "depth": 0,
      "coordinates": "47.35,6.05"
    },
    "category": "blood_candidate",
    "classifiedAt": "2026-02-24T13:50:16.053Z",
    "verification": {
      "verified": true,
      "matchedKeywords": ["blutabnahme"],
      "confidenceScore": 1,
      "pagesScanned": 9
    },
    "prices": [
      "asser ist erlaubt und erwünscht. Preis: 74,39 €",
      "; Befundübermittlung Kosten Diagnostik: 74,39 €",
      "asser ist erlaubt und erwünscht. Preis: 198,02 €",
      "; Befundübermittlung Kosten Diagnostik: 198,02 €",
      "asser ist erlaubt und erwünscht. Preis: 225,15 €",
      "; Befundübermittlung Kosten Diagnostik: 225,15 €",
      "(Sie müssen nicht nüchtern sein) Preis: 64,83 €",
      "; Befundübermittlung Kosten Diagnostik: 64,83 €",
      "(Sie müssen nicht nüchtern sein) Preis: 28,93 €",
      "igungstest durchgeführt. Die Kosten von 53,62 €"
    ],
    "selfPay": false,
    "categoryLabel": "Blutlabor"
  },
  {
    "place_id": "ChIJjUR9rkkpv0cRpxBdB2vmhQU",
    "name": "SYNLAB MVZ Leverkusen",
    "formattedAddress": "Paracelsusstraße 13, 51375 Leverkusen, Germany",
    "location": {
      "lat": 51.0333166,
      "lng": 7.030272699999999
    },
    "website": "https://www.synlab.de/lab/leverkusen",
    "phone": "+49 214 3740",
    "rating": 2.8,
    "types": ["medical_lab", "health", "point_of_interest", "establishment"],
    "status": "OPERATIONAL",
    "sources": ["grid:blood"],
    "source": "google_places",
    "confidenceScore": 0,
    "fetchedAt": "2026-02-24T13:20:17.509Z",
    "searchContext": {
      "pipeline": "blood",
      "tileId": "base_0",
      "keyword": "Bluttest",
      "depth": 0,
      "coordinates": "47.35,6.05"
    },
    "category": "blood_candidate",
    "classifiedAt": "2026-02-24T13:50:16.053Z",
    "verification": {
      "verified": true,
      "matchedKeywords": ["selbstzahler", "blutabnahme"],
      "confidenceScore": 0.5,
      "pagesScanned": 9
    },
    "prices": ["rivat bezahlt werden. Der Preis beträgt 169,03 €"],
    "selfPay": true,
    "categoryLabel": "Blutlabor"
  },
  {
    "place_id": "ChIJ7RayRTCKvkcRFhO7eKORKd0",
    "name": "SYNLAB MVZ Neuwied",
    "formattedAddress": "Dahlbachs Weg 15, 56566 Neuwied, Germany",
    "location": {
      "lat": 50.4713207,
      "lng": 7.4911992
    },
    "website": "https://www.synlab.de/lab/neuwied",
    "phone": "+49 2631 92420",
    "rating": 5,
    "types": ["medical_lab", "health", "point_of_interest", "establishment"],
    "status": "OPERATIONAL",
    "sources": ["grid:blood"],
    "source": "google_places",
    "confidenceScore": 0,
    "fetchedAt": "2026-02-24T13:20:17.510Z",
    "searchContext": {
      "pipeline": "blood",
      "tileId": "base_0",
      "keyword": "Bluttest",
      "depth": 0,
      "coordinates": "47.35,6.05"
    },
    "category": "blood_candidate",
    "classifiedAt": "2026-02-24T13:50:16.053Z",
    "verification": {
      "verified": true,
      "matchedKeywords": ["selbstzahler"],
      "confidenceScore": 0.25,
      "pagesScanned": 9
    },
    "prices": ["rivat bezahlt werden. Der Preis beträgt 169,03 €"],
    "selfPay": true,
    "categoryLabel": "Blutlabor"
  },
  {
    "place_id": "ChIJ33GBebTWuEcR9d1NdLN5Cpc",
    "name": "MVZ SYNLAB Wuppertal",
    "formattedAddress": "Kaiserstraße 72, 42329 Wuppertal, Germany",
    "location": {
      "lat": 51.233119,
      "lng": 7.0751713999999994
    },
    "website": "https://www.synlab.de/lab/wuppertal",
    "phone": "+49 202 725599108",
    "rating": 5,
    "types": ["medical_lab", "health", "point_of_interest", "establishment"],
    "status": "OPERATIONAL",
    "sources": ["grid:blood"],
    "source": "google_places",
    "confidenceScore": 0,
    "fetchedAt": "2026-02-24T13:20:17.510Z",
    "searchContext": {
      "pipeline": "blood",
      "tileId": "base_0",
      "keyword": "Bluttest",
      "depth": 0,
      "coordinates": "47.35,6.05"
    },
    "category": "blood_candidate",
    "classifiedAt": "2026-02-24T13:50:16.053Z",
    "verification": {
      "verified": true,
      "matchedKeywords": ["selbstzahler"],
      "confidenceScore": 0.25,
      "pagesScanned": 9
    },
    "prices": ["rivat bezahlt werden. Der Preis beträgt 169,03 €"],
    "selfPay": true,
    "categoryLabel": "Blutlabor"
  },
  {
    "place_id": "ChIJxQ3F3MDhvkcRpvAhjlRMYZk",
    "name": "CBT Bonn",
    "formattedAddress": "Am Propsthof 3, 53121 Bonn, Germany",
    "location": {
      "lat": 50.7392962,
      "lng": 7.0756045
    },
    "website": "https://www.cbtmed.de/praxen/bonn/",
    "phone": "+49 228 201800",
    "rating": 3.7,
    "types": [
      "doctor",
      "medical_lab",
      "health",
      "point_of_interest",
      "establishment"
    ],
    "status": "OPERATIONAL",
    "sources": ["grid:blood"],
    "source": "google_places",
    "confidenceScore": 0,
    "fetchedAt": "2026-02-24T13:20:17.908Z",
    "searchContext": {
      "pipeline": "blood",
      "tileId": "base_0",
      "keyword": "Blutuntersuchung",
      "depth": 0,
      "coordinates": "47.35,6.05"
    },
    "category": "blood_candidate",
    "classifiedAt": "2026-02-24T13:50:16.053Z",
    "verification": {
      "verified": true,
      "matchedKeywords": ["blutabnahme"],
      "confidenceScore": 0.3,
      "pagesScanned": 9
    },
    "selfPay": false,
    "categoryLabel": "Blutlabor"
  },
  {
    "place_id": "ChIJSY6pjJ0IvUcRHdIFaIDJ7l0",
    "name": "Laborarztpraxis Rhein-Main MVZ GbR",
    "formattedAddress": "Berner Str. 117, 60437 Frankfurt am Main, Germany",
    "location": {
      "lat": 50.190636999999995,
      "lng": 8.657213
    },
    "website": "https://www.laborarztpraxis.de/",
    "phone": "+49 69 669003900",
    "rating": 3.5,
    "types": ["medical_lab", "health", "point_of_interest", "establishment"],
    "status": "OPERATIONAL",
    "sources": ["grid:blood"],
    "source": "google_places",
    "confidenceScore": 0,
    "fetchedAt": "2026-02-24T13:20:18.248Z",
    "searchContext": {
      "pipeline": "blood",
      "tileId": "base_0",
      "keyword": "Blutlabor",
      "depth": 0,
      "coordinates": "47.35,6.05"
    },
    "category": "blood_candidate",
    "classifiedAt": "2026-02-24T13:50:16.053Z",
    "verification": {
      "verified": true,
      "matchedKeywords": ["selbstzahler"],
      "confidenceScore": 0.3,
      "pagesScanned": 8
    },
    "selfPay": true,
    "categoryLabel": "Blutlabor"
  },
  {
    "place_id": "ChIJ_QcCStrDmUcRUVezjUPSqOY",
    "name": "Mein Direktlabor - Labor Stuttgart",
    "formattedAddress": "Leinfelder Str. 60, 70771 Leinfelden-Echterdingen, Germany",
    "location": {
      "lat": 48.6914727,
      "lng": 9.1596611
    },
    "website": "https://www.meindirektlabor.de/",
    "phone": "+49 711 6522430",
    "rating": 4.9,
    "types": ["medical_lab", "health", "point_of_interest", "establishment"],
    "status": "OPERATIONAL",
    "sources": ["grid:blood"],
    "source": "google_places",
    "confidenceScore": 0,
    "fetchedAt": "2026-02-24T13:20:18.249Z",
    "searchContext": {
      "pipeline": "blood",
      "tileId": "base_0",
      "keyword": "Blutlabor",
      "depth": 0,
      "coordinates": "47.35,6.05"
    },
    "category": "blood_candidate",
    "classifiedAt": "2026-02-24T13:50:16.054Z",
    "verification": {
      "verified": true,
      "matchedKeywords": ["selbstzahler", "blutabnahme", "laboranalyse"],
      "confidenceScore": 0.9,
      "pagesScanned": 9
    },
    "selfPay": true,
    "categoryLabel": "Blutlabor"
  },
  {
    "place_id": "ChIJf2SrGxiPsUcRgcuQUAV92pM",
    "name": "Medical Laboratory Hamburg Stephansplatz",
    "formattedAddress": "Stephanspl. 3, 20354 Hamburg, Germany",
    "location": {
      "lat": 53.5578544,
      "lng": 9.9884813
    },
    "website": "https://www.meindirektlabor.de/standorte/standort/labor-stephansplatz/",
    "phone": "+49 40 76696700",
    "rating": 4.8,
    "types": ["medical_lab", "health", "point_of_interest", "establishment"],
    "status": "OPERATIONAL",
    "sources": ["grid:blood"],
    "source": "google_places",
    "confidenceScore": 0,
    "fetchedAt": "2026-02-24T13:20:19.352Z",
    "searchContext": {
      "pipeline": "blood",
      "tileId": "base_0",
      "keyword": "Privatlabor",
      "depth": 0,
      "coordinates": "47.35,6.05"
    },
    "category": "blood_candidate",
    "classifiedAt": "2026-02-24T13:50:16.054Z",
    "verification": {
      "verified": true,
      "matchedKeywords": ["blutabnahme", "laboranalyse"],
      "confidenceScore": 0.6,
      "pagesScanned": 9
    },
    "prices": [
      "sätzliche Kosten für eine Blutentnahme (4,20€",
      "), Abstrichanfertigung (5,36€",
      "ungen (Nahrungsm./Inhalationsallergene) 16,76 €",
      "g in Einzelkomponenten (je Einzelkomp.) 16,76 €",
      "IgE gesamt 16,76 €",
      "ALEX2-Test 180,99 €",
      "e) vorliegen. Transglutaminase-AK (IgA) 30,16 €",
      "IgA-AK gesamt 10,05 €",
      "ie bei uns testen lassen. Creatinkinase 2,68 €",
      "ktionsstörungen auf. Thyreotropin (TSH) 16,76 €"
    ],
    "selfPay": false,
    "categoryLabel": "Blutlabor"
  },
  {
    "place_id": "ChIJi71qmkpRqEcRvP8Zxr2iuDI",
    "name": "Mein Direktlabor - Labor Berlin-Tiergarten",
    "formattedAddress": "Lützowstraße 24-26, 10785 Berlin, Germany",
    "location": {
      "lat": 52.503355199999994,
      "lng": 13.365022999999999
    },
    "website": "https://www.meindirektlabor.de/",
    "phone": "+49 30 48526136",
    "rating": 4.7,
    "types": ["medical_lab", "health", "point_of_interest", "establishment"],
    "status": "OPERATIONAL",
    "sources": ["grid:blood"],
    "source": "google_places",
    "confidenceScore": 0,
    "fetchedAt": "2026-02-24T13:20:19.353Z",
    "searchContext": {
      "pipeline": "blood",
      "tileId": "base_0",
      "keyword": "Privatlabor",
      "depth": 0,
      "coordinates": "47.35,6.05"
    },
    "category": "blood_candidate",
    "classifiedAt": "2026-02-24T13:50:16.054Z",
    "verification": {
      "verified": true,
      "matchedKeywords": ["selbstzahler", "blutabnahme", "laboranalyse"],
      "confidenceScore": 0.9,
      "pagesScanned": 9
    },
    "selfPay": true,
    "categoryLabel": "Blutlabor"
  },
  {
    "place_id": "ChIJffRuKkdXn0cRlNLSiyjP2hI",
    "name": "Mein Direktlabor - Labor Nürnberg",
    "formattedAddress": "EG / Bauteil D, Deutschherrnstraße 15-19, 90429 Nürnberg, Germany",
    "location": {
      "lat": 49.453537499999996,
      "lng": 11.063762599999999
    },
    "website": "https://www.meindirektlabor.de/",
    "phone": "+49 911 9447076",
    "rating": 5,
    "types": ["medical_lab", "health", "point_of_interest", "establishment"],
    "status": "OPERATIONAL",
    "sources": ["grid:blood"],
    "source": "google_places",
    "confidenceScore": 0,
    "fetchedAt": "2026-02-24T13:20:19.353Z",
    "searchContext": {
      "pipeline": "blood",
      "tileId": "base_0",
      "keyword": "Privatlabor",
      "depth": 0,
      "coordinates": "47.35,6.05"
    },
    "category": "blood_candidate",
    "classifiedAt": "2026-02-24T13:50:16.054Z",
    "verification": {
      "verified": true,
      "matchedKeywords": ["selbstzahler", "blutabnahme", "laboranalyse"],
      "confidenceScore": 0.9,
      "pagesScanned": 9
    },
    "selfPay": true,
    "categoryLabel": "Blutlabor"
  },
  {
    "place_id": "ChIJ9RReYrBXqEcRhfev0DAl5Rk",
    "name": "Mein Direktlabor - Labor Berlin-Spandau",
    "formattedAddress": "Siemensdamm 50, 13629 Berlin, Germany",
    "location": {
      "lat": 52.535489299999995,
      "lng": 13.2741213
    },
    "website": "https://www.meindirektlabor.de/",
    "phone": "+49 30 48526208",
    "rating": 5,
    "types": ["medical_lab", "health", "point_of_interest", "establishment"],
    "status": "OPERATIONAL",
    "sources": ["grid:blood"],
    "source": "google_places",
    "confidenceScore": 0,
    "fetchedAt": "2026-02-24T13:20:19.353Z",
    "searchContext": {
      "pipeline": "blood",
      "tileId": "base_0",
      "keyword": "Privatlabor",
      "depth": 0,
      "coordinates": "47.35,6.05"
    },
    "category": "blood_candidate",
    "classifiedAt": "2026-02-24T13:50:16.054Z",
    "verification": {
      "verified": true,
      "matchedKeywords": ["selbstzahler", "blutabnahme", "laboranalyse"],
      "confidenceScore": 0.9,
      "pagesScanned": 9
    },
    "selfPay": true,
    "categoryLabel": "Blutlabor"
  },
  {
    "place_id": "ChIJ-XDeAjnKuEcRjlZqlSvAaHg",
    "name": "Tolab Labor Für Medizinische Diagnostik",
    "formattedAddress": "Hüttenstraße 31a, 40215 Düsseldorf, Germany",
    "location": {
      "lat": 51.21633,
      "lng": 6.7838199999999995
    },
    "website": "http://www.tolab.de/",
    "phone": "+49 211 377384",
    "rating": 3.3,
    "types": ["medical_lab", "health", "point_of_interest", "establishment"],
    "status": "OPERATIONAL",
    "sources": ["grid:blood"],
    "source": "google_places",
    "confidenceScore": 0,
    "fetchedAt": "2026-02-24T13:20:21.371Z",
    "searchContext": {
      "pipeline": "blood",
      "tileId": "base_0.0",
      "keyword": "Privatlabor",
      "depth": 1,
      "coordinates": "47.28,5.98"
    },
    "category": "blood_candidate",
    "classifiedAt": "2026-02-24T13:50:16.054Z",
    "verification": {
      "verified": true,
      "matchedKeywords": ["selbstzahler"],
      "confidenceScore": 0.25,
      "pagesScanned": 9
    },
    "selfPay": true,
    "categoryLabel": "Blutlabor"
  },
  {
    "place_id": "ChIJ7eM72D8dvEcR7rTd65RV3Fk",
    "name": "Meinlabtest GmbH",
    "formattedAddress": "Siegburger Str. 231, 50679 Köln, Germany",
    "location": {
      "lat": 50.9233392,
      "lng": 6.9809826
    },
    "website": "https://meinlabtest.de/",
    "phone": "+49 271 3846000",
    "rating": 2.5,
    "types": [
      "consultant",
      "health",
      "service",
      "point_of_interest",
      "establishment"
    ],
    "status": "OPERATIONAL",
    "sources": ["grid:blood"],
    "source": "google_places",
    "confidenceScore": 0,
    "fetchedAt": "2026-02-24T13:21:28.421Z",
    "searchContext": {
      "pipeline": "blood",
      "tileId": "base_1.1",
      "keyword": "Bluttest",
      "depth": 1,
      "coordinates": "47.28,6.42"
    },
    "category": "blood_candidate",
    "classifiedAt": "2026-02-24T13:50:16.054Z",
    "verification": {
      "verified": true,
      "matchedKeywords": ["blutabnahme", "laboranalyse"],
      "confidenceScore": 0.55,
      "pagesScanned": 2
    },
    "prices": [
      "e Produkte Einzeltests Details Jod Test 49,00 €",
      "Details Allergietest Plus 199,00 €",
      "Details Cortisol Test 29,00 €",
      "Details Testosteron-Test 37,50 €",
      "Details Vitamin-D Test 35,00 €",
      "inierte Tests Details Schwermetall-Test 89,00 €",
      "Details Mikrobiom-Test 169,00 €",
      "Details Hormontest Frau 129,00 €",
      "Details Blutprofil XL (Bluttest) 145,00 €",
      "Details Nutri-Gene Pro (DNA Test) 375,00 €"
    ],
    "selfPay": false,
    "categoryLabel": "Blutlabor"
  },
  {
    "place_id": "ChIJLZENLdqSC0ER-Ka-wlbm4WU",
    "name": "SYNLAB MVZ Ettlingen",
    "formattedAddress": "Otto-Hahn-Straße 18, 76275 Ettlingen, Germany",
    "location": {
      "lat": 48.9445207,
      "lng": 8.378003099999999
    },
    "website": "https://www.synlab.de/lab/ettlingen",
    "phone": "+49 7243 51601",
    "rating": 3.8,
    "types": ["medical_lab", "health", "point_of_interest", "establishment"],
    "status": "OPERATIONAL",
    "sources": ["grid:blood"],
    "source": "google_places",
    "confidenceScore": 0,
    "fetchedAt": "2026-02-24T13:26:09.886Z",
    "searchContext": {
      "pipeline": "blood",
      "tileId": "base_7.0",
      "keyword": "Blutlabor",
      "depth": 1,
      "coordinates": "47.28,8.07"
    },
    "category": "blood_candidate",
    "classifiedAt": "2026-02-24T13:50:16.055Z",
    "verification": {
      "verified": true,
      "matchedKeywords": ["selbstzahler", "blutabnahme", "laboranalyse"],
      "confidenceScore": 0.75,
      "pagesScanned": 9
    },
    "prices": ["rivat bezahlt werden. Der Preis beträgt 169,03 €"],
    "selfPay": true,
    "categoryLabel": "Blutlabor"
  },
  {
    "place_id": "ChIJ6deYLxzHl0cRNz-YJsSqgLQ",
    "name": "SYNLAB MVZ Heidelberg",
    "formattedAddress": "Wasserturmstraße 71, 69214 Eppelheim, Germany",
    "location": {
      "lat": 49.406888099999996,
      "lng": 8.6263741
    },
    "website": "https://www.synlab.de/lab/heidelberg",
    "phone": "+49 6221 7930",
    "rating": 3.1,
    "types": ["medical_lab", "health", "point_of_interest", "establishment"],
    "status": "OPERATIONAL",
    "sources": ["grid:blood"],
    "source": "google_places",
    "confidenceScore": 0,
    "fetchedAt": "2026-02-24T13:26:09.886Z",
    "searchContext": {
      "pipeline": "blood",
      "tileId": "base_7.0",
      "keyword": "Blutlabor",
      "depth": 1,
      "coordinates": "47.28,8.07"
    },
    "category": "blood_candidate",
    "classifiedAt": "2026-02-24T13:50:16.055Z",
    "verification": {
      "verified": true,
      "matchedKeywords": ["selbstzahler"],
      "confidenceScore": 0.25,
      "pagesScanned": 9
    },
    "prices": ["rivat bezahlt werden. Der Preis beträgt 169,03 €"],
    "selfPay": true,
    "categoryLabel": "Blutlabor"
  },
  {
    "place_id": "ChIJuQQrTaL3mkcR4nYMPnBj9is",
    "name": "Labor Dr. Brunner, Labormedizinisches Versorgungszentrum Konstanz GmbH",
    "formattedAddress": "Luisenstraße 7e, 78464 Konstanz, Germany",
    "location": {
      "lat": 47.673176299999994,
      "lng": 9.1876742
    },
    "website": "https://www.labor-brunner.de/",
    "phone": "+49 7531 81730",
    "rating": 4.4,
    "types": ["medical_lab", "health", "point_of_interest", "establishment"],
    "status": "OPERATIONAL",
    "sources": ["grid:blood"],
    "source": "google_places",
    "confidenceScore": 0,
    "fetchedAt": "2026-02-24T13:28:34.284Z",
    "searchContext": {
      "pipeline": "blood",
      "tileId": "base_9.3",
      "keyword": "Bluttest",
      "depth": 1,
      "coordinates": "47.42,8.82"
    },
    "category": "blood_candidate",
    "classifiedAt": "2026-02-24T13:50:16.055Z",
    "verification": {
      "verified": true,
      "matchedKeywords": ["ohne überweisung"],
      "confidenceScore": 0.25,
      "pagesScanned": 9
    },
    "selfPay": true,
    "categoryLabel": "Blutlabor"
  },
  {
    "place_id": "ChIJkRCMKHGEnEcRdB-Wb9yXZyE",
    "name": "Dental Labor Haas GmbH Sonthofen im Allgäu",
    "formattedAddress": "Hindelanger Str. 7, 87527 Sonthofen, Germany",
    "location": {
      "lat": 47.512324,
      "lng": 10.2817797
    },
    "website": "https://www.dental-labor-haas.de/",
    "phone": "+49 8321 3262",
    "rating": 4,
    "types": ["health", "point_of_interest", "establishment"],
    "status": "OPERATIONAL",
    "sources": ["grid:blood"],
    "source": "google_places",
    "confidenceScore": 0,
    "fetchedAt": "2026-02-24T13:30:37.486Z",
    "searchContext": {
      "pipeline": "blood",
      "tileId": "base_14",
      "keyword": "Labor",
      "depth": 0,
      "coordinates": "47.35,10.25"
    },
    "category": "blood_candidate",
    "classifiedAt": "2026-02-24T13:50:16.056Z",
    "verification": {
      "verified": true,
      "matchedKeywords": ["privatleistung"],
      "confidenceScore": 0.6,
      "pagesScanned": 4
    },
    "selfPay": true,
    "categoryLabel": "Blutlabor"
  },
  {
    "place_id": "ChIJ2dfDv5YLsEcRQeJB5rMn0TM",
    "name": "Lang W. Prof. Dr.med., Maschek Prof. Dr.med., Delventhal S. Dr.med.",
    "formattedAddress": "Feodor-Lynen-Straße 21, 30625 Hannover, Germany",
    "location": {
      "lat": 52.3895431,
      "lng": 9.799683199999999
    },
    "website": "https://www.synlab.de/lab/hannover",
    "phone": "+49 511 2351010",
    "rating": 3,
    "types": ["medical_lab", "health", "point_of_interest", "establishment"],
    "status": "OPERATIONAL",
    "sources": ["city:Hannover", "grid:78"],
    "source": "google_places",
    "fetchedAt": "2026-02-23T14:11:23.767Z",
    "searchContext": {
      "city": "Hannover",
      "query": "laboratory Hannover"
    },
    "category": "blood_candidate",
    "classifiedAt": "2026-02-23T14:44:58.155Z",
    "verification": {
      "verified": true,
      "matchedKeywords": ["selbstzahler"],
      "confidenceScore": 0.25,
      "pagesScanned": 9
    }
  },
  {
    "place_id": "ChIJnRNyG6R0sEcRXku3rXKUZwM",
    "name": "Labor Hannover MVZ GmbH",
    "formattedAddress": "Großer Kolonnenweg 18C, 30163 Hannover, Germany",
    "location": {
      "lat": 52.406109,
      "lng": 9.738871
    },
    "website": "https://labor-augsburg-mvz.de/laborgruppe/labor-hannover-mvz",
    "phone": "+49 511 8562570",
    "rating": 4.4,
    "types": ["medical_lab", "health", "point_of_interest", "establishment"],
    "status": "OPERATIONAL",
    "sources": ["city:Hannover"],
    "source": "google_places",
    "fetchedAt": "2026-02-23T14:11:23.767Z",
    "searchContext": {
      "city": "Hannover",
      "query": "laboratory Hannover"
    },
    "category": "blood_candidate",
    "classifiedAt": "2026-02-23T14:44:58.155Z",
    "verification": {
      "verified": true,
      "matchedKeywords": ["blutabnahme"],
      "confidenceScore": 0.35,
      "pagesScanned": 9
    }
  },
  {
    "place_id": "ChIJIQjIg3f2r0cRgubzMKC7adY",
    "name": "HIB Blutanalyselabor Unternehmergesellschaft (haftungsbeschränkt)",
    "formattedAddress": "Papenstieg 8, 38100 Braunschweig, Germany",
    "location": {
      "lat": 52.2651695,
      "lng": 10.5227357
    },
    "website": "http://blutanalyselabor.de/",
    "phone": "+49 531 2311325",
    "rating": 4.5,
    "types": ["medical_lab", "point_of_interest", "health", "establishment"],
    "status": "OPERATIONAL",
    "sources": ["city:Braunschweig"],
    "source": "google_places",
    "fetchedAt": "2026-02-23T14:11:29.747Z",
    "searchContext": {
      "city": "Braunschweig",
      "query": "laboratory Braunschweig"
    },
    "category": "blood_candidate",
    "classifiedAt": "2026-02-23T14:44:58.161Z",
    "verification": {
      "verified": true,
      "matchedKeywords": ["blutabnahme"],
      "confidenceScore": 0.3,
      "pagesScanned": 6
    }
  },
  {
    "place_id": "ChIJO81s5XbmuUcR2bhX7_Wmjs4",
    "name": "Medizinisches Versorgungszentrum Zentrum für Tumordiagnostik und -therapie",
    "formattedAddress": "Am Natruper Holz 69, 49076 Osnabrück, Germany",
    "location": {
      "lat": 52.2890002,
      "lng": 8.010814
    },
    "website": "https://www.niels-stensen-kliniken.de/marienhospital-osnabrueck.html",
    "phone": "+49 541 9664800",
    "rating": 3,
    "types": ["doctor", "health", "point_of_interest", "establishment"],
    "status": "OPERATIONAL",
    "sources": ["city:Osnabrück"],
    "source": "google_places",
    "fetchedAt": "2026-02-23T14:11:38.319Z",
    "searchContext": {
      "city": "Osnabrück",
      "query": "DEXA Osnabrück"
    },
    "category": "blood_candidate",
    "classifiedAt": "2026-02-23T14:44:58.178Z",
    "verification": {
      "verified": true,
      "matchedKeywords": ["laboranalyse"],
      "confidenceScore": 0.25,
      "pagesScanned": 9
    }
  },
  {
    "place_id": "ChIJg_hVUavftkcRJJqebweKYyQ",
    "name": "Mein Direktlabor - Labor Oldenburg",
    "formattedAddress": "Koppelstraße 1, 26135 Oldenburg, Germany",
    "location": {
      "lat": 53.1351229,
      "lng": 8.2179222
    },
    "website": "https://www.meindirektlabor.de/standorte/standort/labor-oldenburg/",
    "phone": "+49 441 36140833",
    "rating": 5,
    "types": ["medical_lab", "health", "point_of_interest", "establishment"],
    "status": "OPERATIONAL",
    "sources": ["city:Oldenburg"],
    "source": "google_places",
    "fetchedAt": "2026-02-23T14:11:41.575Z",
    "searchContext": {
      "city": "Oldenburg",
      "query": "laboratory Oldenburg"
    },
    "category": "blood_candidate",
    "classifiedAt": "2026-02-23T14:44:58.180Z",
    "verification": {
      "verified": true,
      "matchedKeywords": ["blutabnahme", "laboranalyse"],
      "confidenceScore": 0.75,
      "pagesScanned": 9
    }
  },
  {
    "place_id": "ChIJ31XpG1iuukcR1hCi2jO28nc",
    "name": "Institut für Bildgebende Diagnostik und Interventionelle Radiologie | Helios Klinikum Hildesheim",
    "formattedAddress": "Senator-Braun-Allee 33, 31135 Hildesheim, Germany",
    "location": {
      "lat": 52.1516586,
      "lng": 9.9758649
    },
    "website": "https://www.helios-gesundheit.de/standorte-angebote/kliniken/hildesheim/leistungen/fachbereiche/radiologie/",
    "phone": "+49 5121 8942702",
    "rating": 1,
    "types": ["medical_clinic", "health", "point_of_interest", "establishment"],
    "status": "OPERATIONAL",
    "sources": ["city:Hildesheim", "grid:45"],
    "source": "google_places",
    "fetchedAt": "2026-02-23T14:11:53.598Z",
    "searchContext": {
      "city": "Hildesheim",
      "query": "diagnostic center Hildesheim"
    },
    "category": "blood_candidate",
    "classifiedAt": "2026-02-23T14:44:58.205Z",
    "verification": {
      "verified": true,
      "matchedKeywords": ["selbstzahler"],
      "confidenceScore": 0.25,
      "pagesScanned": 9
    }
  },
  {
    "place_id": "ChIJQ2sLOlqSr0cR5_9UhQWEscw",
    "name": "ZEUS (Zentrum für Entwicklungsdiagnostik und Sozialpädiatrie) am Klinikum Wolfsburg",
    "formattedAddress": "Sauerbruchstraße 5a, 38440 Wolfsburg, Germany",
    "location": {
      "lat": 52.4116321,
      "lng": 10.76769
    },
    "website": "https://www.klinikum.wolfsburg.de/kliniken/institute-und-zentren/sozialpaediatrisches-zentrum-spz-zeus/",
    "phone": "+49 5361 801389",
    "rating": 3.3,
    "types": [
      "hospital",
      "health",
      "point_of_interest",
      "service",
      "establishment"
    ],
    "status": "OPERATIONAL",
    "sources": ["city:Wolfsburg"],
    "source": "google_places",
    "fetchedAt": "2026-02-23T14:12:04.712Z",
    "searchContext": {
      "city": "Wolfsburg",
      "query": "medical center Wolfsburg"
    },
    "category": "blood_candidate",
    "classifiedAt": "2026-02-23T14:44:58.212Z",
    "verification": {
      "verified": true,
      "matchedKeywords": ["selbstzahler"],
      "confidenceScore": 0.3,
      "pagesScanned": 9
    }
  },
  {
    "place_id": "ChIJJcsJfVmSr0cRfkdFm6ix04Y",
    "name": "Klinikum Wolfsburg, Klinik für bildgebende Diagnostik und interventionelle Radiologie",
    "formattedAddress": "Sauerbruchstraße 7, 38440 Wolfsburg, Germany",
    "location": {
      "lat": 52.414359999999995,
      "lng": 10.76775
    },
    "website": "https://www.klinikum.wolfsburg.de/kliniken/radiologie",
    "phone": "+49 5361 801511",
    "rating": 4.3,
    "types": [
      "doctor",
      "medical_clinic",
      "health",
      "point_of_interest",
      "establishment"
    ],
    "status": "OPERATIONAL",
    "sources": ["city:Wolfsburg", "grid:48", "grid:63", "grid:66", "grid:81"],
    "source": "google_places",
    "fetchedAt": "2026-02-23T14:12:05.013Z",
    "searchContext": {
      "city": "Wolfsburg",
      "query": "diagnostic center Wolfsburg"
    },
    "category": "blood_candidate",
    "classifiedAt": "2026-02-23T14:44:58.212Z",
    "verification": {
      "verified": true,
      "matchedKeywords": ["selbstzahler"],
      "confidenceScore": 0.3,
      "pagesScanned": 9
    }
  },
  {
    "place_id": "ChIJJcsJfVmSr0cRPi4neggAZAA",
    "name": "Klinikum der Stadt Wolfsburg Institut für Klinische Chemie, Laboratoriums- und Transfusionsmedizin",
    "formattedAddress": "Sauerbruchstraße 7, 38440 Wolfsburg, Germany",
    "location": {
      "lat": 52.414359999999995,
      "lng": 10.76775
    },
    "website": "https://www.klinikum.wolfsburg.de/kliniken/institute-und-zentren/institut-fuer-labormedizin",
    "phone": "+49 5361 801700",
    "rating": 5,
    "types": ["medical_lab", "point_of_interest", "health", "establishment"],
    "status": "OPERATIONAL",
    "sources": ["city:Wolfsburg", "grid:81"],
    "source": "google_places",
    "fetchedAt": "2026-02-23T14:12:05.335Z",
    "searchContext": {
      "city": "Wolfsburg",
      "query": "laboratory Wolfsburg"
    },
    "category": "blood_candidate",
    "classifiedAt": "2026-02-23T14:44:58.212Z",
    "verification": {
      "verified": true,
      "matchedKeywords": ["selbstzahler"],
      "confidenceScore": 0.3,
      "pagesScanned": 9
    }
  },
  {
    "place_id": "ChIJc8RUha0isEcR9l1j1OBhr5E",
    "name": "MVZ Medizinisches Labor Celle GmbH",
    "formattedAddress": "Neumarkt 1, 29223 Celle, Germany",
    "location": {
      "lat": 52.626428399999995,
      "lng": 10.0796379
    },
    "website": "https://www.ml-celle.de/",
    "phone": "+49 5141 92560",
    "rating": 4.7,
    "types": ["medical_lab", "health", "point_of_interest", "establishment"],
    "status": "OPERATIONAL",
    "sources": ["city:Celle"],
    "source": "google_places",
    "fetchedAt": "2026-02-23T14:12:22.902Z",
    "searchContext": {
      "city": "Celle",
      "query": "medical center Celle"
    },
    "category": "blood_candidate",
    "classifiedAt": "2026-02-23T14:44:58.219Z",
    "verification": {
      "verified": true,
      "matchedKeywords": ["laboranalyse"],
      "confidenceScore": 0.25,
      "pagesScanned": 9
    }
  },
  {
    "place_id": "ChIJIcQrierrtkcRQtLreekffOQ",
    "name": "SYNLAB MVZ Jade-Weser",
    "formattedAddress": "Beethovenstraße 2, 26316 Varel, Germany",
    "location": {
      "lat": 53.390521,
      "lng": 8.1398181
    },
    "website": "https://www.synlab.de/lab/jade-weser",
    "phone": "+49 4451 951982402",
    "rating": 3.4,
    "types": ["medical_lab", "health", "point_of_interest", "establishment"],
    "status": "OPERATIONAL",
    "sources": ["city:Jever", "grid:123"],
    "source": "google_places",
    "fetchedAt": "2026-02-23T14:13:16.850Z",
    "searchContext": {
      "city": "Jever",
      "query": "laboratory Jever"
    },
    "category": "blood_candidate",
    "classifiedAt": "2026-02-23T14:44:58.249Z",
    "verification": {
      "verified": true,
      "matchedKeywords": ["selbstzahler"],
      "confidenceScore": 0.25,
      "pagesScanned": 9
    }
  },
  {
    "place_id": "ChIJ_5LnVhuwuEcRCj2ernpa3P0",
    "name": "Clinic for Diagnostic and Interventional Radiology | Helios Hospital Krefeld",
    "formattedAddress": "Lutherpl. 40, 47805 Krefeld, Germany",
    "location": {
      "lat": 51.3200572,
      "lng": 6.5657822
    },
    "website": "https://www.helios-gesundheit.de/standorte-angebote/kliniken/krefeld/leistungen/fachbereiche/radiologie/",
    "phone": "+49 2151 322561",
    "rating": 4.8,
    "types": ["medical_clinic", "health", "point_of_interest", "establishment"],
    "status": "OPERATIONAL",
    "sources": ["grid:0", "grid:18"],
    "source": "google_places",
    "fetchedAt": "2026-02-23T14:13:51.933Z",
    "searchContext": {
      "tileId": 0,
      "keyword": "diagnostic center",
      "coordinates": "51.45,6.75"
    },
    "category": "blood_candidate",
    "classifiedAt": "2026-02-23T14:44:58.262Z",
    "verification": {
      "verified": true,
      "matchedKeywords": ["selbstzahler"],
      "confidenceScore": 0.25,
      "pagesScanned": 9
    }
  },
  {
    "place_id": "ChIJO_AwmhG_uEcRh0i6VwjeKmk",
    "name": "Gerinnungszentrum Rhein-Ruhr GZRR",
    "formattedAddress": "Königstraße 13, 47051 Duisburg, Germany",
    "location": {
      "lat": 51.43355390000001,
      "lng": 6.7662663
    },
    "website": "https://www.gzrr.de/",
    "phone": "+49 203 3483360",
    "rating": 4.2,
    "types": [
      "medical_lab",
      "doctor",
      "medical_clinic",
      "health",
      "point_of_interest",
      "establishment"
    ],
    "status": "OPERATIONAL",
    "sources": ["grid:0", "grid:18"],
    "source": "google_places",
    "fetchedAt": "2026-02-23T14:13:52.196Z",
    "searchContext": {
      "tileId": 0,
      "keyword": "clinical laboratory",
      "coordinates": "51.45,6.75"
    },
    "category": "blood_candidate",
    "classifiedAt": "2026-02-23T14:44:58.262Z",
    "verification": {
      "verified": true,
      "matchedKeywords": ["blutabnahme"],
      "confidenceScore": 0.3,
      "pagesScanned": 9
    }
  },
  {
    "place_id": "ChIJdTWjHgQXuUcRNGQlDSZGLq8",
    "name": "Somnolab",
    "formattedAddress": "Am Kai 10, 44263 Dortmund, Germany",
    "location": {
      "lat": 51.490874,
      "lng": 7.5066742
    },
    "website": "https://www.somnolab.de/",
    "phone": "+49 231 94113040",
    "rating": 4.4,
    "types": ["medical_clinic", "health", "point_of_interest", "establishment"],
    "status": "OPERATIONAL",
    "sources": ["grid:3"],
    "source": "google_places",
    "fetchedAt": "2026-02-23T14:13:54.051Z",
    "searchContext": {
      "tileId": 3,
      "keyword": "clinical laboratory",
      "coordinates": "51.45,7.65"
    },
    "category": "blood_candidate",
    "classifiedAt": "2026-02-23T14:44:58.265Z",
    "verification": {
      "verified": true,
      "matchedKeywords": ["selbstzahler"],
      "confidenceScore": 0.25,
      "pagesScanned": 9
    }
  },
  {
    "place_id": "ChIJF4Ig2Z7hvkcR7mMDLE0Bqm0",
    "name": "SYNLAB MVZ Bonn",
    "formattedAddress": "Dechenstraße 1, 53115 Bonn, Germany",
    "location": {
      "lat": 50.731316199999995,
      "lng": 7.096895399999999
    },
    "website": "https://www.synlab.de/lab/bonn",
    "phone": "+49 228 555260",
    "rating": 4.4,
    "types": ["medical_lab", "point_of_interest", "health", "establishment"],
    "status": "OPERATIONAL",
    "sources": [
      "grid:6",
      "grid:9",
      "grid:12",
      "grid:15",
      "grid:24",
      "grid:27",
      "grid:30",
      "grid:33",
      "grid:39",
      "grid:42",
      "grid:45",
      "grid:48",
      "grid:57",
      "grid:60",
      "grid:63",
      "grid:66",
      "grid:72",
      "grid:75",
      "grid:78",
      "grid:81",
      "grid:84",
      "grid:87",
      "grid:93",
      "grid:99",
      "grid:102",
      "grid:105",
      "grid:108",
      "grid:117",
      "grid:120",
      "grid:123",
      "grid:126",
      "grid:135",
      "grid:138",
      "grid:141",
      "grid:144",
      "grid:150"
    ],
    "source": "google_places",
    "fetchedAt": "2026-02-23T14:13:55.952Z",
    "searchContext": {
      "tileId": 6,
      "keyword": "clinical laboratory",
      "coordinates": "51.45,8.55"
    },
    "category": "blood_candidate",
    "classifiedAt": "2026-02-23T14:44:58.267Z",
    "verification": {
      "verified": true,
      "matchedKeywords": ["selbstzahler", "blutabnahme"],
      "confidenceScore": 0.5,
      "pagesScanned": 9
    }
  },
  {
    "place_id": "ChIJmdkQJco4u0cRBEYehVlVGZg",
    "name": "SYNLAB MVZ Hessen GmbH",
    "formattedAddress": "Kurt-Wolters-Straße 2-4, 34125 Kassel, Germany",
    "location": {
      "lat": 51.3206042,
      "lng": 9.5030134
    },
    "website": "https://www.synlab.de/lab/hessen",
    "phone": "+49 561 766440",
    "rating": 4.4,
    "types": ["medical_lab", "health", "point_of_interest", "establishment"],
    "status": "OPERATIONAL",
    "sources": ["grid:9"],
    "source": "google_places",
    "fetchedAt": "2026-02-23T14:13:57.798Z",
    "searchContext": {
      "tileId": 9,
      "keyword": "clinical laboratory",
      "coordinates": "51.45,9.45"
    },
    "category": "blood_candidate",
    "classifiedAt": "2026-02-23T14:44:58.271Z",
    "verification": {
      "verified": true,
      "matchedKeywords": ["selbstzahler"],
      "confidenceScore": 0.25,
      "pagesScanned": 9
    }
  },
  {
    "place_id": "ChIJez3pj-Ilv0cRPzVkkoMxZuw",
    "name": "prohealth Testzentrum Köln",
    "formattedAddress": "Hohenzollernring 26, 50672 Köln, Germany",
    "location": {
      "lat": 50.9381172,
      "lng": 6.939734499999999
    },
    "website": "https://www.prohealth-koeln.de/",
    "phone": "+49 1514 1644494",
    "rating": 5,
    "types": [
      "medical_lab",
      "medical_clinic",
      "point_of_interest",
      "health",
      "establishment"
    ],
    "status": "OPERATIONAL",
    "sources": [
      "grid:12",
      "grid:15",
      "grid:33",
      "grid:48",
      "grid:81",
      "grid:84",
      "grid:90",
      "grid:93",
      "grid:99",
      "grid:105",
      "grid:108",
      "grid:117",
      "grid:120",
      "grid:123",
      "grid:126",
      "grid:138",
      "grid:141",
      "grid:144",
      "grid:30",
      "grid:66",
      "grid:135",
      "grid:150"
    ],
    "source": "google_places",
    "fetchedAt": "2026-02-23T14:13:59.649Z",
    "searchContext": {
      "tileId": 12,
      "keyword": "clinical laboratory",
      "coordinates": "51.45,10.35"
    },
    "category": "blood_candidate",
    "classifiedAt": "2026-02-23T14:44:58.272Z",
    "verification": {
      "verified": true,
      "matchedKeywords": ["selbstzahler"],
      "confidenceScore": 0.25,
      "pagesScanned": 2
    }
  },
  {
    "place_id": "ChIJM31dA50nsUcR7gCAsow0gZM",
    "name": "Radiologie Zentrum Bremen im medicum | Brustdiagnostik, Sonographie, Knochendichtemessung",
    "formattedAddress": "Schwachhauser Heerstraße 50, 28209 Bremen, Germany",
    "location": {
      "lat": 53.0822088,
      "lng": 8.8343916
    },
    "website": "https://radiologie-zentrum-bremen.de/",
    "phone": "+49 421 841313400",
    "rating": 4.9,
    "types": ["medical_clinic", "health", "point_of_interest", "establishment"],
    "status": "OPERATIONAL",
    "sources": ["grid:93", "grid:108"],
    "source": "google_places",
    "fetchedAt": "2026-02-23T14:14:51.215Z",
    "searchContext": {
      "tileId": 93,
      "keyword": "diagnostic center",
      "coordinates": "52.95,9.15"
    },
    "category": "dexa_candidate",
    "classifiedAt": "2026-02-23T14:44:58.302Z",
    "verification": {
      "verified": true,
      "matchedKeywords": ["dexa"],
      "confidenceScore": 0.3,
      "pagesScanned": 9
    }
  },
  {
    "place_id": "ChIJ0XuvGxiPsUcRZsvhuRAo7IE",
    "name": "Dermatologikum Hamburg",
    "formattedAddress": "Stephanspl. 5, 20354 Hamburg, Germany",
    "location": {
      "lat": 53.5580578,
      "lng": 9.9885346
    },
    "website": "https://www.dermatologikum.de/",
    "phone": "+49 40 3510750",
    "rating": 4.5,
    "types": [
      "medical_lab",
      "skin_care_clinic",
      "doctor",
      "medical_clinic",
      "point_of_interest",
      "health",
      "establishment"
    ],
    "status": "OPERATIONAL",
    "sources": [
      "grid:96",
      "grid:111",
      "grid:114",
      "grid:129",
      "grid:132",
      "grid:147"
    ],
    "source": "google_places",
    "fetchedAt": "2026-02-23T14:14:53.326Z",
    "searchContext": {
      "tileId": 96,
      "keyword": "clinical laboratory",
      "coordinates": "52.95,10.05"
    },
    "category": "blood_candidate",
    "classifiedAt": "2026-02-23T14:44:58.305Z",
    "verification": {
      "verified": true,
      "matchedKeywords": ["selbstzahler"],
      "confidenceScore": 0.65,
      "pagesScanned": 9
    }
  },
  {
    "place_id": "ChIJ_RNuoZWFsUcRE2MbgzYYpA0",
    "name": "MEDILYS Laborgesellschaft mbH - Transfusionsmedizin",
    "formattedAddress": "Geschäftsführung, Paul-Ehrlich-Straße 1, 22763 Hamburg, Germany",
    "location": {
      "lat": 53.5543081,
      "lng": 9.899413899999999
    },
    "website": "https://www.medilys.de/fachgebiete/transfusionsmedizin/",
    "phone": "+49 40 1818852000",
    "rating": null,
    "types": ["medical_clinic", "health", "point_of_interest", "establishment"],
    "status": "OPERATIONAL",
    "sources": ["grid:129"],
    "source": "google_places",
    "fetchedAt": "2026-02-23T14:15:13.843Z",
    "searchContext": {
      "tileId": 129,
      "keyword": "diagnostic center",
      "coordinates": "53.55,9.75"
    },
    "category": "blood_candidate",
    "classifiedAt": "2026-02-23T14:44:58.315Z",
    "verification": {
      "verified": true,
      "matchedKeywords": ["laboranalyse"],
      "confidenceScore": 0.25,
      "pagesScanned": 5
    }
  },
  {
    "place_id": "ChIJqS9rfrqFsUcR5UzeWX27z50",
    "name": "MEDILYS Laborgesellschaft mbH - Infektionsserologie",
    "formattedAddress": "Geschäftsführung, Paul-Ehrlich-Straße 1, 22763 Hamburg, Germany",
    "location": {
      "lat": 53.5543081,
      "lng": 9.899413899999999
    },
    "website": "https://www.medilys.de/fachgebiete/infektionsserologie/",
    "phone": "+49 40 1818815900",
    "rating": null,
    "types": ["medical_clinic", "health", "point_of_interest", "establishment"],
    "status": "OPERATIONAL",
    "sources": ["grid:129"],
    "source": "google_places",
    "fetchedAt": "2026-02-23T14:15:13.843Z",
    "searchContext": {
      "tileId": 129,
      "keyword": "diagnostic center",
      "coordinates": "53.55,9.75"
    },
    "category": "blood_candidate",
    "classifiedAt": "2026-02-23T14:44:58.315Z",
    "verification": {
      "verified": true,
      "matchedKeywords": ["laboranalyse"],
      "confidenceScore": 0.25,
      "pagesScanned": 5
    }
  },
  {
    "place_id": "ChIJkeQNcLyFsUcR9AHjdm1p3Gc",
    "name": "MEDILYS Laborgesellschaft mbH - Molekulargenetik",
    "formattedAddress": "Geschäftsführung, Paul-Ehrlich-Straße 1, 22763 Hamburg, Germany",
    "location": {
      "lat": 53.5543081,
      "lng": 9.899413899999999
    },
    "website": "https://www.medilys.de/fachgebiete/molekulargenetik/",
    "phone": "+49 40 1818815900",
    "rating": null,
    "types": ["medical_clinic", "health", "point_of_interest", "establishment"],
    "status": "OPERATIONAL",
    "sources": ["grid:129"],
    "source": "google_places",
    "fetchedAt": "2026-02-23T14:15:13.843Z",
    "searchContext": {
      "tileId": 129,
      "keyword": "diagnostic center",
      "coordinates": "53.55,9.75"
    },
    "category": "blood_candidate",
    "classifiedAt": "2026-02-23T14:44:58.315Z",
    "verification": {
      "verified": true,
      "matchedKeywords": ["laboranalyse"],
      "confidenceScore": 0.25,
      "pagesScanned": 5
    }
  },
  {
    "place_id": "ChIJN6updxWFsUcRiS0MP1ExCfE",
    "name": "MEDILYS Laborgesellschaft mbH - Hämostaseologie",
    "formattedAddress": "Geschäftsführung, Paul-Ehrlich-Straße 1, 22763 Hamburg, Germany",
    "location": {
      "lat": 53.5543081,
      "lng": 9.899413899999999
    },
    "website": "https://www.medilys.de/fachgebiete/haemostaseologie/",
    "phone": "+49 40 1818815900",
    "rating": null,
    "types": ["medical_clinic", "health", "point_of_interest", "establishment"],
    "status": "OPERATIONAL",
    "sources": ["grid:129"],
    "source": "google_places",
    "fetchedAt": "2026-02-23T14:15:13.843Z",
    "searchContext": {
      "tileId": 129,
      "keyword": "diagnostic center",
      "coordinates": "53.55,9.75"
    },
    "category": "blood_candidate",
    "classifiedAt": "2026-02-23T14:44:58.315Z",
    "verification": {
      "verified": true,
      "matchedKeywords": ["laboranalyse"],
      "confidenceScore": 0.25,
      "pagesScanned": 5
    }
  },
  {
    "place_id": "ChIJlYr2SUyFsUcRupzzDVMkTz4",
    "name": "MEDILYS Laborgesellschaft mbH - Klinische Chemie",
    "formattedAddress": "Geschäftsführung, Paul-Ehrlich-Straße 1, 22763 Hamburg, Germany",
    "location": {
      "lat": 53.5543081,
      "lng": 9.899413899999999
    },
    "website": "https://www.medilys.de/fachgebiete/klinische-chemie/",
    "phone": "+49 40 1818815900",
    "rating": null,
    "types": ["medical_clinic", "health", "point_of_interest", "establishment"],
    "status": "OPERATIONAL",
    "sources": ["grid:129"],
    "source": "google_places",
    "fetchedAt": "2026-02-23T14:15:13.843Z",
    "searchContext": {
      "tileId": 129,
      "keyword": "diagnostic center",
      "coordinates": "53.55,9.75"
    },
    "category": "blood_candidate",
    "classifiedAt": "2026-02-23T14:44:58.315Z",
    "verification": {
      "verified": true,
      "matchedKeywords": ["laboranalyse"],
      "confidenceScore": 0.25,
      "pagesScanned": 5
    }
  },
  {
    "place_id": "ChIJUVJLZKSFsUcRUeXvvAW2KpU",
    "name": "MEDILYS Laborgesellschaft mbH - Hygiene / Krankenhaushygiene",
    "formattedAddress": "Geschäftsführung, Paul-Ehrlich-Straße 1, 22763 Hamburg, Germany",
    "location": {
      "lat": 53.5543081,
      "lng": 9.899413899999999
    },
    "website": "https://www.medilys.de/fachgebiete/hygiene/",
    "phone": "+49 40 1818815900",
    "rating": null,
    "types": ["medical_clinic", "health", "point_of_interest", "establishment"],
    "status": "OPERATIONAL",
    "sources": ["grid:129"],
    "source": "google_places",
    "fetchedAt": "2026-02-23T14:15:13.843Z",
    "searchContext": {
      "tileId": 129,
      "keyword": "diagnostic center",
      "coordinates": "53.55,9.75"
    },
    "category": "blood_candidate",
    "classifiedAt": "2026-02-23T14:44:58.315Z",
    "verification": {
      "verified": true,
      "matchedKeywords": ["laboranalyse"],
      "confidenceScore": 0.25,
      "pagesScanned": 5
    }
  },
  {
    "place_id": "ChIJf2SrGxiPsUcRgcuQUAV92pM",
    "name": "Medical Laboratory Hamburg Stephansplatz",
    "formattedAddress": "Stephanspl. 3, 20354 Hamburg, Germany",
    "location": {
      "lat": 53.5578544,
      "lng": 9.9884813
    },
    "website": "https://www.meindirektlabor.de/standorte/standort/labor-stephansplatz/",
    "phone": "+49 40 76696700",
    "rating": 4.8,
    "types": ["medical_lab", "health", "point_of_interest", "establishment"],
    "status": "OPERATIONAL",
    "sources": ["grid:129", "grid:132", "grid:144", "grid:147"],
    "source": "google_places",
    "fetchedAt": "2026-02-23T14:15:14.124Z",
    "searchContext": {
      "tileId": 129,
      "keyword": "clinical laboratory",
      "coordinates": "53.55,9.75"
    },
    "category": "blood_candidate",
    "classifiedAt": "2026-02-23T14:44:58.316Z",
    "verification": {
      "verified": true,
      "matchedKeywords": ["blutabnahme", "laboranalyse"],
      "confidenceScore": 0.6,
      "pagesScanned": 9
    }
  },
  {
    "place_id": "ChIJwafN_D6MsUcRacoliC236w8",
    "name": "SYNLAB MVZ Hamburg",
    "formattedAddress": "Osterbekstraße 90C, 22083 Hamburg, Germany",
    "location": {
      "lat": 53.5829263,
      "lng": 10.029233
    },
    "website": "https://www.synlab.de/lab/hamburg",
    "phone": "+49 40 6506040",
    "rating": 4,
    "types": ["medical_lab", "health", "point_of_interest", "establishment"],
    "status": "OPERATIONAL",
    "sources": ["grid:129"],
    "source": "google_places",
    "fetchedAt": "2026-02-23T14:15:14.125Z",
    "searchContext": {
      "tileId": 129,
      "keyword": "clinical laboratory",
      "coordinates": "53.55,9.75"
    },
    "category": "blood_candidate",
    "classifiedAt": "2026-02-23T14:44:58.316Z",
    "verification": {
      "verified": true,
      "matchedKeywords": ["selbstzahler"],
      "confidenceScore": 0.25,
      "pagesScanned": 9
    }
  },
  {
    "place_id": "ChIJgQ-Jw48nskcRks9rp5Wyb9k",
    "name": "Asklepios Klinik Nord - Heidberg - Pathologie / Neuropathologie",
    "formattedAddress": "Tangstedter Landstraße 400, 22417 Hamburg, Germany",
    "location": {
      "lat": 53.6746589,
      "lng": 10.0286829
    },
    "website": "https://www.asklepios.com/hamburg/nord/heidberg/experten/pathologie-neuropathologie/",
    "phone": "+49 40 1818873092",
    "rating": null,
    "types": ["medical_clinic", "health", "point_of_interest", "establishment"],
    "status": "OPERATIONAL",
    "sources": ["grid:147"],
    "source": "google_places",
    "fetchedAt": "2026-02-23T14:15:25.070Z",
    "searchContext": {
      "tileId": 147,
      "keyword": "diagnostic center",
      "coordinates": "53.80,10.05"
    },
    "category": "blood_candidate",
    "classifiedAt": "2026-02-23T14:44:58.321Z",
    "verification": {
      "verified": true,
      "matchedKeywords": ["selbstzahler"],
      "confidenceScore": 0.25,
      "pagesScanned": 6
    }
  }
]
